odoo/addons/partner_customer_supplier/README.rst
odoo/addons/partner_customer_supplier/__init__.py
odoo/addons/partner_customer_supplier/__manifest__.py
odoo/addons/partner_customer_supplier/i18n/partner_customer_supplier.pot
odoo/addons/partner_customer_supplier/models/__init__.py
odoo/addons/partner_customer_supplier/models/res_partner.py
odoo/addons/partner_customer_supplier/readme/CONTRIBUTORS.rst
odoo/addons/partner_customer_supplier/readme/CREDITS.rst
odoo/addons/partner_customer_supplier/readme/DESCRIPTION.rst
odoo/addons/partner_customer_supplier/static/description/icon.png
odoo/addons/partner_customer_supplier/static/description/index.html
odoo/addons/partner_customer_supplier/tests/__init__.py
odoo/addons/partner_customer_supplier/tests/test_res_partner.py
odoo/addons/partner_customer_supplier/views/res_partner_views.xml
odoo_addon_partner_customer_supplier-15.0.1.0.0.3.dist-info/METADATA
odoo_addon_partner_customer_supplier-15.0.1.0.0.3.dist-info/WHEEL
odoo_addon_partner_customer_supplier-15.0.1.0.0.3.dist-info/top_level.txt
odoo_addon_partner_customer_supplier-15.0.1.0.0.3.dist-info/RECORD
